[{"name":"Al Gh\u0101nim","slug":"al ghanim","region":"01","country":"QA","latitude":"25.27987","longitude":"51.54037","population":19010},{"name":"Al Hil\u0101l al Gharb\u012byah","slug":"al hilal al gharbiyah","region":"01","country":"QA","latitude":"25.2586","longitude":"51.53098","population":15461},{"name":"Al Hil\u0101l ash Sharq\u012byah","slug":"al hilal ash sharqiyah","region":"01","country":"QA","latitude":"25.26042","longitude":"51.54632","population":15461},{"name":"Al Khawr","slug":"al khawr","region":"04","country":"QA","latitude":"25.68389","longitude":"51.50583","population":18923},{"name":"Al Man\u015f\u016brah","slug":"al mansurah","region":"01","country":"QA","latitude":"25.26807","longitude":"51.53219","population":65493},{"name":"Al Ma\u0163\u0101r al \u2018At\u012bq","slug":"al matar al 'atiq","region":"01","country":"QA","latitude":"25.25138","longitude":"51.55569","population":76774},{"name":"Al Wakrah","slug":"al wakrah","region":"10","country":"QA","latitude":"25.17151","longitude":"51.60337","population":26436},{"name":"Al \u2018Unayzah","slug":"al 'unayzah","region":"01","country":"QA","latitude":"25.33759","longitude":"51.50953","population":39761},{"name":"An Najmah","slug":"an najmah","region":"01","country":"QA","latitude":"25.26704","longitude":"51.54322","population":43695},{"name":"Ar Rayy\u0101n","slug":"ar rayyan","region":"06","country":"QA","latitude":"25.29194","longitude":"51.42444","population":272465},{"name":"As Sadd","slug":"as sadd","region":"01","country":"QA","latitude":"25.28617","longitude":"51.50074","population":36077},{"name":"As Sul\u0163ah al Jad\u012bdah","slug":"as sultah al jadidah","region":"01","country":"QA","latitude":"25.2604","longitude":"51.51403","population":27432},{"name":"Ath Thum\u0101mah Khams\u016bn","slug":"ath thumamah khamsun","region":"01","country":"QA","latitude":"25.21958","longitude":"51.55323","population":22284},{"name":"Ath Thum\u0101mah Sab\u2018ah wa Arba\u2018\u016bn","slug":"ath thumamah sab'ah wa arba'un","region":"01","country":"QA","latitude":"25.23903","longitude":"51.56333","population":22284},{"name":"Ath Thum\u0101mah Sittah wa Arba\u2018\u016bn","slug":"ath thumamah sittah wa arba'un","region":"01","country":"QA","latitude":"25.23404","longitude":"51.54053","population":22284},{"name":"Az\u0327 Z\u0327a\u2018\u0101yin","slug":"az za'ayin","region":"13","country":"QA","latitude":"25.57744","longitude":"51.48306","population":54339},{"name":"Doha","slug":"doha","region":"01","country":"QA","latitude":"25.28545","longitude":"51.53096","population":344939},{"name":"Far\u012bj Kulayb","slug":"farij kulayb","region":"01","country":"QA","latitude":"25.31313","longitude":"51.4929","population":33263},{"name":"Far\u012bj al Am\u012br","slug":"farij al amir","region":"06","country":"QA","latitude":"25.28733","longitude":"51.47136","population":33263},{"name":"Mad\u012bnat Khal\u012bfah","slug":"madinat khalifah","region":"01","country":"QA","latitude":"25.32047","longitude":"51.47787","population":44459},{"name":"Mu\u2018aydhir Raw\u1e11at R\u0101shid","slug":"mu'aydhir rawdat rashid","region":"06","country":"QA","latitude":"25.2617","longitude":"51.39684","population":27569},{"name":"Nu\u2018ayjah","slug":"nu'ayjah","region":"01","country":"QA","latitude":"25.24617","longitude":"51.53227","population":19975},{"name":"Umm Ghuwayl\u012bnah","slug":"umm ghuwaylinah","region":"14","country":"QA","latitude":"25.58716","longitude":"51.14986","population":39457},{"name":"Umm Lakhb\u0101","slug":"umm lakhba","region":"01","country":"QA","latitude":"25.34157","longitude":"51.4706","population":16993},{"name":"Umm \u015eal\u0101l Mu\u1e29ammad","slug":"umm salal muhammad","region":"09","country":"QA","latitude":"25.41524","longitude":"51.40647","population":29391}]