[{"name":"Beitbridge","slug":"beitbridge","region":"07","country":"ZW","latitude":"-22.21667","longitude":"30","population":58574},{"name":"Bindura","slug":"bindura","region":"03","country":"ZW","latitude":"-17.30192","longitude":"31.33056","population":50400},{"name":"Bulawayo","slug":"bulawayo","region":"09","country":"ZW","latitude":"-20.15","longitude":"28.58333","population":665952},{"name":"Chegutu","slug":"chegutu","region":"05","country":"ZW","latitude":"-18.13021","longitude":"30.14074","population":65800},{"name":"Chinhoyi","slug":"chinhoyi","region":"05","country":"ZW","latitude":"-17.36667","longitude":"30.2","population":90800},{"name":"Chipinge","slug":"chipinge","region":"01","country":"ZW","latitude":"-20.18833","longitude":"32.62365","population":34959},{"name":"Chiredzi","slug":"chiredzi","region":"08","country":"ZW","latitude":"-21.05","longitude":"31.66667","population":40100},{"name":"Chitungwiza","slug":"chitungwiza","region":"10","country":"ZW","latitude":"-18.01274","longitude":"31.07555","population":371246},{"name":"Epworth","slug":"epworth","region":"10","country":"ZW","latitude":"-17.89","longitude":"31.1475","population":206368},{"name":"Gokwe","slug":"gokwe","region":"02","country":"ZW","latitude":"-18.20476","longitude":"28.9349","population":33073},{"name":"Gwanda","slug":"gwanda","region":"07","country":"ZW","latitude":"-20.93622","longitude":"29.00698","population":26700},{"name":"Gweru","slug":"gweru","region":"02","country":"ZW","latitude":"-19.45","longitude":"29.81667","population":158200},{"name":"Harare","slug":"harare","region":"10","country":"ZW","latitude":"-17.82772","longitude":"31.05337","population":1542813},{"name":"Harare Western Suburbs","slug":"harare western suburbs","region":"05","country":"ZW","latitude":"-17.8415","longitude":"30.87674","population":15556},{"name":"Hwange","slug":"hwange","region":"06","country":"ZW","latitude":"-18.36446","longitude":"26.49877","population":39750},{"name":"Kadoma","slug":"kadoma","region":"05","country":"ZW","latitude":"-18.33328","longitude":"29.91534","population":117381},{"name":"Kariba","slug":"kariba","region":"05","country":"ZW","latitude":"-16.51667","longitude":"28.8","population":27600},{"name":"Karoi","slug":"karoi","region":"05","country":"ZW","latitude":"-16.80993","longitude":"29.69247","population":37564},{"name":"Kwekwe","slug":"kwekwe","region":"02","country":"ZW","latitude":"-18.92809","longitude":"29.81486","population":119863},{"name":"Marondera","slug":"marondera","region":"04","country":"ZW","latitude":"-18.18527","longitude":"31.55193","population":66204},{"name":"Masvingo","slug":"masvingo","region":"08","country":"ZW","latitude":"-20.06373","longitude":"30.82766","population":90286},{"name":"Mutare","slug":"mutare","region":"01","country":"ZW","latitude":"-18.9707","longitude":"32.67086","population":224802},{"name":"Mvurwi","slug":"mvurwi","region":"03","country":"ZW","latitude":"-17.03333","longitude":"30.85","population":15646},{"name":"Norton","slug":"norton","region":"05","country":"ZW","latitude":"-17.88333","longitude":"30.7","population":87039},{"name":"Redcliff","slug":"redcliff","region":"02","country":"ZW","latitude":"-19.03333","longitude":"29.78333","population":41526},{"name":"Rusape","slug":"rusape","region":"01","country":"ZW","latitude":"-18.52785","longitude":"32.12843","population":37906},{"name":"Ruwa","slug":"ruwa","region":"04","country":"ZW","latitude":"-17.88972","longitude":"31.24472","population":94083},{"name":"Shurugwi","slug":"shurugwi","region":"02","country":"ZW","latitude":"-19.67016","longitude":"30.00589","population":23304},{"name":"Victoria Falls","slug":"victoria falls","region":"06","country":"ZW","latitude":"-17.93285","longitude":"25.83066","population":35215},{"name":"Zvishavane","slug":"zvishavane","region":"08","country":"ZW","latitude":"-20.32674","longitude":"30.06648","population":59717}]